hikvision_nvr_downloader/__init__.py
hikvision_nvr_downloader/convert.py
hikvision_nvr_downloader/hikvision_nvr_downloader.py
hikvision_nvr_downloader/utils.py
hikvision_nvr_downloader-0.2.0.dist-info/METADATA
hikvision_nvr_downloader-0.2.0.dist-info/WHEEL
hikvision_nvr_downloader-0.2.0.dist-info/top_level.txt
hikvision_nvr_downloader-0.2.0.dist-info/RECORD
