Metadata-Version: 2.4
Name: hikvision-nvr-downloader
Version: 0.2.0
Summary: A robust, flexible Python library to search and download recorded clips from a Hikvision NVR.
Author-email: Abhishek Chopra <choprabhishek630@gmail.com>
Project-URL: Homepage, https://github.com/choprabhishek630/hikvision-nvr-downloader
Project-URL: Bug Tracker, https://github.com/choprabhishek630/hikvision-nvr-downloader/issues
Classifier: Programming Language :: Python :: 3
Classifier: License :: OSI Approved :: MIT License
Classifier: Operating System :: OS Independent
Requires-Python: >=3.7
Requires-Dist: requests>=2.25.1
